data_mesh_cli/DataMeshCli.py
data_mesh_cli/__init__.py
data_mesh_util/DataMeshAdmin.py
data_mesh_util/DataMeshConsumer.py
data_mesh_util/DataMeshMacros.py
data_mesh_util/DataMeshProducer.py
data_mesh_util/__init__.py
data_mesh_util/lib/ApiAutomator.py
data_mesh_util/lib/SubscriberTracker.py
data_mesh_util/lib/__init__.py
data_mesh_util/lib/constants.py
data_mesh_util/lib/utils.py
data_mesh_util/resource/consumer_account_policy.pystache
data_mesh_util/resource/consumer_mesh_policy.pystache
data_mesh_util/resource/data_mesh_read_only_policy.pystache
data_mesh_util/resource/data_mesh_setup_iam_policy.pystache
data_mesh_util/resource/enable_crawler_role.pystache
data_mesh_util/resource/glue_ram_optin.pystache
data_mesh_util/resource/lf_cross_account_tbac.pystache
data_mesh_util/resource/producer_account_policy.pystache
data_mesh_util/resource/producer_bucket_policy.pystache
data_mesh_util/resource/producer_mesh_policy.pystache
aws_data_mesh_utils-1.0.16.dist-info/LICENSE
aws_data_mesh_utils-1.0.16.dist-info/METADATA
aws_data_mesh_utils-1.0.16.dist-info/NOTICE
aws_data_mesh_utils-1.0.16.dist-info/WHEEL
aws_data_mesh_utils-1.0.16.dist-info/top_level.txt
aws_data_mesh_utils-1.0.16.dist-info/RECORD
