Metadata-Version: 2.1
Name: aws-data-mesh-utils
Version: 1.0.16
Summary: The AWS Data Mesh Helper library provides automation around the most common tasks that customers need to perform to implement a data mesh architecture on AWS.
Home-page: https://github.com/aws-samples/aws-data-mesh-utils
Author: Ian Meyers
Author-email: meyersi@amazon.co.uk
License: Apache 2.0
Project-URL: Bug Tracker, https://github.com/aws-samples/aws-data-mesh-utils/issues
Platform: UNKNOWN
Classifier: Programming Language :: Python :: 3
Classifier: License :: OSI Approved :: Apache Software License
Classifier: Operating System :: OS Independent
Requires-Python: >=3.6
License-File: LICENSE
License-File: NOTICE
Requires-Dist: boto3 (~=1.20.51)
Requires-Dist: pystache (~=0.6.0)
Requires-Dist: setuptools (~=60.8.1)
Requires-Dist: shortuuid (~=1.0.8)
Requires-Dist: botocore (~=1.23.51)
